waterworksai/__init__.py
waterworksai/client.py
waterworksai/exceptions.py
waterworksai/adapters/__init__.py
waterworksai/adapters/dataframe.py
waterworksai/adapters/json.py
waterworksai-3.0.0.dist-info/LICENSE
waterworksai-3.0.0.dist-info/METADATA
waterworksai-3.0.0.dist-info/WHEEL
waterworksai-3.0.0.dist-info/top_level.txt
waterworksai-3.0.0.dist-info/RECORD
