Metadata-Version: 2.1
Name: waterworksai
Version: 3.0.0
Summary: Official Python client for waterworks.ai API
Author: D. Rehn
Classifier: Programming Language :: Python :: 3
Classifier: License :: OSI Approved :: MIT License
Classifier: Operating System :: OS Independent
Classifier: Development Status :: 5 - Production/Stable
Classifier: Intended Audience :: Developers
Classifier: Topic :: Scientific/Engineering :: Hydrology
Requires-Python: >=3.9
License-File: LICENSE
Requires-Dist: pandas >=1.5
Requires-Dist: requests >=2.28
